main.py
report_builder_Monaco_race/__init__.py
report_builder_Monaco_race/report.py
report_builder_Monaco_race/report_builder.py
report_builder_Monaco_race-0.0.1.dist-info/LICENSE
report_builder_Monaco_race-0.0.1.dist-info/METADATA
report_builder_Monaco_race-0.0.1.dist-info/WHEEL
report_builder_Monaco_race-0.0.1.dist-info/top_level.txt
report_builder_Monaco_race-0.0.1.dist-info/RECORD
