Metadata-Version: 2.1
Name: report-builder-Monaco-race
Version: 0.0.1
Summary: A small package that make report of Monaco race in 2018
Author-email: Nataliia Kaptur <vasyliva.nv@gmail.com>
Project-URL: Homepage, http://git.foxminded.ua/foxstudent104833/task-6-report-of-monaco-2018-racing.git
Classifier: Programming Language :: Python :: 3
Classifier: License :: OSI Approved :: MIT License
Classifier: Operating System :: OS Independent
Requires-Python: >=3.8
License-File: LICENSE
Requires-Dist: pandas
Requires-Dist: parameterized (>=0.9.0)
